<?xml version="1.0" encoding="UTF-8"?>
<bio:treatment xmlns:bio="http://www.github.com/biosemantics" xmlns:xsi="http://www.w3.org/2001/XMLSchema-instance" xsi:schemaLocation="http://www.github.com/biosemantics http://www.w3.org/2001/XMLSchema-instance">
  <meta>
    <source>
      <author>unknown</author>
      <date>unknown</date>
    </source>
  </meta>
  <taxon_identification status="ACCEPTED">
    <taxon_name rank="family" authority="Martinov" date="unknown">asteraceae</taxon_name>
    <taxon_name rank="tribe" authority="Cassini" date="1819">astereae</taxon_name>
    <taxon_name rank="genus" authority="Nees" date="1832">symphyotrichum</taxon_name>
    <taxon_name rank="subgenus" authority="unknown" date="unknown">symphyotrichum</taxon_name>
    <taxon_name rank="section" authority="unknown" date="unknown">symphyotrichum</taxon_name>
    <taxon_name rank="species" authority="(Wiegand) G. L. Nesom" date="1995">ontarionis</taxon_name>
    <taxon_name rank="variety" authority="unknown" date="unknown">ontarionis</taxon_name>
    <taxon_hierarchy>family asteraceae;tribe astereae;genus symphyotrichum;subgenus symphyotrichum;section symphyotrichum;species ontarionis;variety ontarionis</taxon_hierarchy>
  </taxon_identification>
  <description type="morphology">Leaves: abaxial faces moderately to densely hairy. 2n = 32.</description>
  <description type="phenology">aug</description>
  <description type="phenology">summer</description>
  <description type="phenology">sep</description>
  <description type="phenology">fall</description>
  <description type="phenology">oct</description>
  <description type="habitat">often shaded</description>
  <description type="habitat">usually moist, alluvial soils</description>
  <description type="habitat">alluvial stream or lake shores</description>
  <description type="habitat">floodplain deciduous forests or thickets</description>
  <description type="habitat">bogs</description>
  <description type="habitat">marshes</description>
  <description type="habitat">edges of fields</description>
  <description type="habitat">roadsides</description>
  <description type="elevation">10–300+ m;</description>
  <description type="distribution">Ont.</description>
  <description type="distribution">Que.</description>
  <description type="distribution">Ala.</description>
  <description type="distribution">Ill.</description>
  <description type="distribution">Ind.</description>
  <description type="distribution">Iowa</description>
  <description type="distribution">Kans.</description>
  <description type="distribution">Ky.</description>
  <description type="distribution">La.</description>
  <description type="distribution">Mich.</description>
  <description type="distribution">Minn.</description>
  <description type="distribution">Miss.</description>
  <description type="distribution">Mo.</description>
  <description type="distribution">Nebr.</description>
  <description type="distribution">N.Y.</description>
  <description type="distribution">N.C.</description>
  <description type="distribution">Okla.</description>
  <description type="distribution">Pa.</description>
  <description type="distribution">S.Dak.</description>
  <description type="distribution">Tenn.</description>
  <description type="distribution">Tex.</description>
  <description type="distribution">Vt.</description>
  <description type="distribution">Wis.</description>
  <number>49a.</number>
  <discussion>A. G. Jones (1989) suggested that var. ontarionis hybridizes with Symphyotrichum lanceolatum, S. lateriflorum, and S. racemosum. Existence of such hybrids needs confirmation.</discussion>
</bio:treatment>
