<?xml version="1.0" encoding="UTF-8"?>
<bio:treatment xmlns:bio="http://www.github.com/biosemantics" xmlns:xsi="http://www.w3.org/2001/XMLSchema-instance" xsi:schemaLocation="http://www.github.com/biosemantics http://www.w3.org/2001/XMLSchema-instance">
  <meta>
    <source>
      <author>unknown</author>
      <date>unknown</date>
    </source>
  </meta>
  <taxon_identification status="ACCEPTED">
    <taxon_name rank="family" authority="Martinov" date="unknown">Asteraceae</taxon_name>
    <taxon_name rank="tribe" authority="Cassini" date="unknown">Astereae</taxon_name>
    <taxon_name rank="genus" authority="unknown" date="unknown">Erigeron</taxon_name>
    <taxon_name rank="species" authority="G. L. Nesom &amp; W. A. Weber" date="unknown">lackschewitzii</taxon_name>
    <place_of_publication>
      <publication_title>Madroño</publication_title>
      <place_in_publication>30: 245, fig. 1. 1983</place_in_publication>
    </place_of_publication>
    <taxon_hierarchy>family Asteraceae;tribe Astereae;genus Erigeron;species lackschewitzii;</taxon_hierarchy>
  </taxon_identification>
  <description type="morphology">Perennials, 3.5–8 cm; taprooted, caudices simple or branched, relatively long, woody. Stems erect (scapiform), loosely white lanate-villous, sometimes sparsely minutely glandular. Leaves basal (persistent) and cauline (leaf bases broadened or not, not thickened and whitish-indurate); basal blades linear-oblanceolate to narrowly oblanceolate, 20–60 × 1.2–3 mm, cauline (on proximal 1/2 of stems) similar to basal or slightly reduced, margins entire (apices acute), adaxial faces loosely strigose to villous (or hairs mixed, appressed and spreading), abaxial glabrate, eglandular. Heads 1. Involucres 6–8 × 12–17 mm. Phyllaries in 3 series, densely white-villous (hairs sometimes with blackish purple cross walls), densely minutely glandular. Ray florets 30–68; corollas purple to lavender, 8–11 mm, laminae coiling. Disc corollas 3.5–4.3 mm. Cypselae 2.3–2.8 mm, 2-nerved, faces strigose; pappi: outer of setae and scales, inner of 15–24 bristles.</description>
  <description type="phenology">jul</description>
  <description type="phenology">summer</description>
  <description type="phenology">aug</description>
  <description type="habitat">rocky slopes and ridges</description>
  <description type="habitat">terraces</description>
  <description type="habitat">talus</description>
  <description type="habitat">dry meadows</description>
  <description type="habitat">usually calcareous</description>
  <description type="elevation">2200–2500 m;</description>
  <description type="distribution">Alta.</description>
  <description type="distribution">Mont.</description>
  <number>43.</number>
  <other_name type="common_name">Lackschewitz fleabane</other_name>
  <discussion>Erigeron lackschewitzii is closely similar to E. ochroleucus and perhaps derived from it.</discussion>
</bio:treatment>
