<?xml version="1.0" encoding="UTF-8"?>
<bio:treatment xmlns:bio="http://www.github.com/biosemantics" xmlns:xsi="http://www.w3.org/2001/XMLSchema-instance" xsi:schemaLocation="http://www.github.com/biosemantics http://www.w3.org/2001/XMLSchema-instance">
  <meta>
    <source>
      <author>unknown</author>
      <date>unknown</date>
    </source>
  </meta>
  <taxon_identification status="ACCEPTED">
    <taxon_name rank="family" authority="Martinov" date="unknown">Asteraceae</taxon_name>
    <taxon_name rank="tribe" authority="Cassini" date="unknown">Astereae</taxon_name>
    <taxon_name rank="genus" authority="unknown" date="unknown">Erigeron</taxon_name>
    <taxon_name rank="species" authority="(Greenman) G. L. Nesom" date="unknown">versicolor</taxon_name>
    <place_of_publication>
      <publication_title>Sida</publication_title>
      <place_in_publication>9: 225. 1982</place_in_publication>
    </place_of_publication>
    <taxon_hierarchy>family Asteraceae;tribe Astereae;genus Erigeron;species versicolor;</taxon_hierarchy>
  </taxon_identification>
  <taxon_identification status="BASIONYM">
    <taxon_name rank="genus" authority="unknown" date="unknown">Achaetogeron</taxon_name>
    <taxon_name rank="species" authority="Greenman" date="unknown">versicolor</taxon_name>
    <place_of_publication>
      <publication_title>Proc. Amer. Acad. Arts</publication_title>
      <place_in_publication>41: 255. 1905</place_in_publication>
    </place_of_publication>
    <taxon_hierarchy>genus Achaetogeron;species versicolor;</taxon_hierarchy>
  </taxon_identification>
  <taxon_identification status="SYNONYM">
    <taxon_name rank="genus" authority="unknown" date="unknown">Achaetogeron</taxon_name>
    <taxon_name rank="species" authority="Larsen" date="unknown">chihuahuensis</taxon_name>
    <taxon_hierarchy>genus Achaetogeron;species chihuahuensis;</taxon_hierarchy>
  </taxon_identification>
  <taxon_identification status="SYNONYM">
    <taxon_name rank="genus" authority="unknown" date="unknown">Erigeron</taxon_name>
    <taxon_name rank="species" authority="Shinners" date="unknown">geiseri</taxon_name>
    <taxon_name rank="variety" authority="Shinners" date="unknown">calcicola</taxon_name>
    <taxon_hierarchy>genus Erigeron;species geiseri;variety calcicola;</taxon_hierarchy>
  </taxon_identification>
  <taxon_identification status="SYNONYM">
    <taxon_name rank="genus" authority="unknown" date="unknown">Erigeron</taxon_name>
    <taxon_name rank="species" authority="Wooton &amp; Standley" date="unknown">gilensis</taxon_name>
    <taxon_hierarchy>genus Erigeron;species gilensis;</taxon_hierarchy>
  </taxon_identification>
  <taxon_identification status="SYNONYM">
    <taxon_name rank="genus" authority="unknown" date="unknown">Erigeron</taxon_name>
    <taxon_name rank="species" authority="Shinners" date="unknown">mimegletes</taxon_name>
    <taxon_hierarchy>genus Erigeron;species mimegletes;</taxon_hierarchy>
  </taxon_identification>
  <number>168.</number>
  <other_name type="common_name">Bald-fruit fleabane</other_name>
  <discussion>In Arizona, Erigeron versicolor grows in meadows, along creeks, and in pine-aspen-spruce areas.</discussion>
  <discussion>Erigeron versicolor is distinguished by its annual duration, nodding buds, conic receptacles, broad phyllaries, and pappi of only minute crowns. The species appears to be disjunctly divided among three regions in the United States and Mexico (D. C. D. De Jong and G. L. Nesom 1996), and habitats vary widely. This is an unusual distribution. There is much variation in duration, root type, orientation of stem pubescence, elaboration of the pappus crown, and achene vestiture, and this morphologic variation does not appear to be strongly correlated with geography.</discussion>
</bio:treatment>
