<?xml version="1.0" encoding="UTF-8"?>
<bio:treatment xmlns:bio="http://www.github.com/biosemantics" xmlns:xsi="http://www.w3.org/2001/XMLSchema-instance" xsi:schemaLocation="http://www.github.com/biosemantics http://www.w3.org/2001/XMLSchema-instance">
  <meta>
    <source>
      <author>John L. Strother</author>
      <date>unknown</date>
    </source>
  </meta>
  <taxon_identification status="ACCEPTED">
    <taxon_name rank="family" authority="Martinov" date="unknown">asteraceae</taxon_name>
    <taxon_name rank="tribe" authority="Lamarck &amp; de Candolle" date="1806">cichorieae</taxon_name>
    <taxon_name rank="genus" authority="Linnaeus" date="1754">CICHORIUM</taxon_name>
    <place_of_publication>
      <publication_title>Sp. Pl.</publication_title>
      <place_in_publication>2: 813. 1753</place_in_publication>
    </place_of_publication>
    <place_of_publication>
      <publication_title>Gen. Pl. ed.</publication_title>
      <place_in_publication>5, 354. 1754</place_in_publication>
    </place_of_publication>
    <taxon_hierarchy>family asteraceae;tribe cichorieae;genus CICHORIUM</taxon_hierarchy>
    <other_info_on_name type="etymology">[Ancient Arabic name]</other_info_on_name>
  </taxon_identification>
  <description type="morphology">Perennials [annuals, biennials], [2–]10–120+ cm; taprooted. Stems usually 1, erect, branched distally or throughout, setose or hispid to pilose, or glabrous. Leaves basal and cauline; usually sessile; basal blades oblanceolate to lance-linear, margins usually runcinate-pinnate to dentate, rarely entire; cauline similar, smaller, margins dentate or entire. Heads mostly in glomerules (axillary and nearly sessile), some borne singly (on ± elongate peduncles). Peduncles (dimorphic: most 0–2 mm, some 12–85+ mm): the longer often slightly inflated distally, not bracteate. Calyculi 0 (or interpreted as outer phyllaries). Involucres ± cylindric, 3–5+ mm diam. Phyllaries 10–15+ in 2+ series, lance-ovate to lanceolate or linear, unequal, margins little, if at all, scarious, apices obtuse to acute. Receptacles flat, pitted, ± hispid, usually epaleate. Florets 8–25+; corollas usually blue [purple], sometimes pink or white. Cypselae brownish, ± prismatic (3–5-angled), not beaked, faces smooth, glabrous; pappi persistent, coroniform (of 40–60+, whitish, subequal, erose scales in 1–2 series). x = 9.</description>
  <description type="distribution">introduced; Europe, n Africa, Asia; introduced also in South America, Africa, Pacific Old World.</description>
  <number>35.</number>
  <discussion>Species 6 (1 in the flora):</discussion>
  <discussion>The salad green known as endive (Cichorium endivia Linnaeus) may sometimes be found as an escape from gardens or agricultural plantings. It differs from C. intybus in having purple corollas, cypselae 1.5–2.5 mm, and pappi 0.6–1+ mm.</discussion>
</bio:treatment>
