<?xml version="1.0" encoding="UTF-8"?>
<bio:treatment xmlns:bio="http://www.github.com/biosemantics" xmlns:xsi="http://www.w3.org/2001/XMLSchema-instance" xsi:schemaLocation="http://www.github.com/biosemantics http://www.w3.org/2001/XMLSchema-instance">
  <meta>
    <source>
      <author>unknown</author>
      <date>unknown</date>
    </source>
  </meta>
  <taxon_identification status="ACCEPTED">
    <taxon_name rank="genus" authority="unknown" date="unknown">Corydalis</taxon_name>
    <taxon_name rank="species" authority="(Linnaeus) Persoon" date="unknown">sempervirens</taxon_name>
    <place_of_publication>
      <publication_title>Syn. Pl.</publication_title>
      <place_in_publication>2: 269. 1807</place_in_publication>
    </place_of_publication>
    <taxon_hierarchy>genus Corydalis;species sempervirens;</taxon_hierarchy>
  </taxon_identification>
  <taxon_identification status="BASIONYM">
    <taxon_name rank="genus" authority="unknown" date="unknown">Fumaria</taxon_name>
    <taxon_name rank="species" authority="Linnaeus" date="unknown">sempervirens</taxon_name>
    <place_of_publication>
      <publication_title>Sp. Pl.</publication_title>
      <place_in_publication>2: 700. 1753</place_in_publication>
    </place_of_publication>
    <taxon_hierarchy>genus Fumaria;species sempervirens;</taxon_hierarchy>
  </taxon_identification>
  <taxon_identification status="SYNONYM">
    <taxon_name rank="genus" authority="unknown" date="unknown">Capnoides</taxon_name>
    <taxon_name rank="species" authority="(Linnaeus) Borkhausen" date="unknown">sempervirens</taxon_name>
    <taxon_hierarchy>genus Capnoides;species sempervirens;</taxon_hierarchy>
  </taxon_identification>
  <description type="morphology">Plants biennial, from somewhat succulent roots. Stems usually 1, erect, 0.5-8 dm, very glaucous. Leaves compound; blade with 3-4 orders of leaflets and lobes; ultimate lobes oblong-elliptic, obtuse, apiculate. Inflorescences terminal, racemose or paniculate, 1-8-flowered on each axis; bracts inconspicuous, narrowly elliptic, 2-5 × 0.5-1 mm. Flowers erect; pedicel slender, 5-20 mm; sepals ovate, short-attenuate, to 3 mm; petals pink, tipped yellow; spurred petal 10-15 mm, spur blunt, 3-4 mm, crest absent, marginal wing relatively broad, revolute, unspurred outer petal 10-13 mm; inner petals 9-12 mm, blade broadly obovate, with high, angular keel, claw slender, 6-8 mm; nectariferous spur 1/3 length of petal spur, blunt; style ca. 4 mm; stigma triangular, with 4 papillae. Capsules erect, linear, straight, (25-)30-35(-50) mm. Seeds ca. 1 mm diam., minutely decorated. 2n = 16.</description>
  <description type="phenology">Flowering early summer-early fall</description>
  <description type="habitat">Rock crevices, talus, forest clearings, open woods, and on burned or otherwise disturbed areas in shallow, often dry soil</description>
  <description type="elevation">10-1550 m</description>
  <description type="distribution">Alta</description>
  <description type="distribution">B.C.</description>
  <description type="distribution">Man.</description>
  <description type="distribution">N.B.</description>
  <description type="distribution">Nfld.</description>
  <description type="distribution">N.W.T.</description>
  <description type="distribution">N.S.</description>
  <description type="distribution">Ont.</description>
  <description type="distribution">P.E.I.</description>
  <description type="distribution">Que.</description>
  <description type="distribution">Sask.</description>
  <description type="distribution">Yukon</description>
  <description type="distribution">Alaska</description>
  <description type="distribution">Conn.</description>
  <description type="distribution">Ga.</description>
  <description type="distribution">Ill.</description>
  <description type="distribution">Ind.</description>
  <description type="distribution">Ky.</description>
  <description type="distribution">Maine</description>
  <description type="distribution">Md.</description>
  <description type="distribution">Mass.</description>
  <description type="distribution">Mich.</description>
  <description type="distribution">Minn.</description>
  <description type="distribution">Mont.</description>
  <description type="distribution">N.H.</description>
  <description type="distribution">N.J.</description>
  <description type="distribution">N.Y.</description>
  <description type="distribution">N.C.</description>
  <description type="distribution">Ohio</description>
  <description type="distribution">Pa.</description>
  <description type="distribution">R.I.</description>
  <description type="distribution">S.C.</description>
  <description type="distribution">Tenn.</description>
  <description type="distribution">Vt.</description>
  <description type="distribution">Va.</description>
  <description type="distribution">W.Va.</description>
  <description type="distribution">Wis.</description>
  <number>5.</number>
  <other_name type="common_name">Pink and yellow corydalis</other_name>
  <other_name type="common_name">pale corydalis</other_name>
  <other_name type="common_name">harlequin-flower</other_name>
  <other_name type="common_name">corydale toujours verte</other_name>
  <discussion>endemic</discussion>
  <discussion>illustrated</discussion>
  <discussion>weedy</discussion>
  <discussion>The Iroquois used a decoction prepared from plants of Corydalis sempervirens medicinally to alleviate piles (D. E. Moerman 1986).</discussion>
</bio:treatment>
