<?xml version="1.0" encoding="UTF-8"?>
<bio:treatment xmlns:bio="http://www.github.com/biosemantics" xmlns:xsi="http://www.w3.org/2001/XMLSchema-instance" xsi:schemaLocation="http://www.github.com/biosemantics http://www.w3.org/2001/XMLSchema-instance">
  <meta>
    <source>
      <author>unknown</author>
      <date>unknown</date>
    </source>
  </meta>
  <taxon_identification status="ACCEPTED">
    <taxon_name rank="family" authority="Jussieu" date="unknown">Cactaceae</taxon_name>
    <taxon_name rank="subfamily" authority="Burnett" date="unknown">Opuntioideae</taxon_name>
    <taxon_name rank="genus" authority="unknown" date="unknown">Opuntia</taxon_name>
    <taxon_name rank="species" authority="Haworth" date="unknown">polyacantha</taxon_name>
    <taxon_name rank="variety" authority="(L. D. Benson) B. D. Parfitt" date="unknown">nicholii</taxon_name>
    <place_of_publication>
      <publication_title>Cact. Succ. J. (Los Angeles)</publication_title>
      <place_in_publication>70: 188. 1998</place_in_publication>
    </place_of_publication>
    <taxon_hierarchy>family Cactaceae;subfamily Opuntioideae;genus Opuntia;species polyacantha;variety nicholii;</taxon_hierarchy>
  </taxon_identification>
  <taxon_identification status="BASIONYM">
    <taxon_name rank="genus" authority="unknown" date="unknown">Opuntia</taxon_name>
    <taxon_name rank="species" authority="L. D. Benson" date="unknown">nicholii</taxon_name>
    <place_of_publication>
      <publication_title>Cacti Arizona ed.</publication_title>
      <place_in_publication>2, 48. 1950</place_in_publication>
    </place_of_publication>
    <taxon_hierarchy>genus Opuntia;species nicholii;</taxon_hierarchy>
  </taxon_identification>
  <taxon_identification status="SYNONYM">
    <taxon_name rank="genus" authority="unknown" date="unknown">Opuntia</taxon_name>
    <taxon_name rank="species" authority="Engelmann &amp; J. M. Bigelow" date="unknown">hystricina</taxon_name>
    <taxon_name rank="variety" authority="(L. D. Benson) Backe berg" date="unknown">nicholii</taxon_name>
    <taxon_hierarchy>genus Opuntia;species hystricina;variety nicholii;</taxon_hierarchy>
  </taxon_identification>
  <description type="morphology">Stem segments narrowly to broadly obovate, 10–27 × 7–18 cm; areoles 8–11 per
        diagonal row across midstem segment, 12–30 mm apart. Spines in most areoles, of 2 kinds:
        major spines 1–5 per areole, down curved, ascending near stem segment apex, pink-gray or
        basal 2/3 brown to black, the longest 45–150 mm; minor spines 3–8 per areole, deflexed,
        white to gray, 60–220 cm (spine clusters easily detached in preparing specimens). Fruits
        stout; areoles 18–24, most bearing 3–12 spines, 8–17 mm. 2n = 66.</description>
  <description type="phenology">spring</description>
  <description type="phenology">mar</description>
  <description type="phenology">apr</description>
  <description type="phenology">may</description>
  <description type="habitat">barren areas with saltbush and ephedra, limestone or red, sandy soils</description>
  <description type="elevation">1200–1300 m;</description>
  <description type="distribution">Ariz.</description>
  <description type="distribution">Utah.</description>
  <number>34c.</number>
  <other_name type="common_name">Navajo Bridge pricklypear</other_name>
</bio:treatment>
