<?xml version="1.0" encoding="UTF-8"?>
<bio:treatment xmlns:bio="http://www.github.com/biosemantics" xmlns:xsi="http://www.w3.org/2001/XMLSchema-instance" xsi:schemaLocation="http://www.github.com/biosemantics http://www.w3.org/2001/XMLSchema-instance">
  <meta>
    <source>
      <author>unknown</author>
      <date>unknown</date>
    </source>
  </meta>
  <taxon_identification status="ACCEPTED">
    <taxon_name rank="family" authority="Jussieu" date="unknown">nyctaginaceae</taxon_name>
    <taxon_name rank="genus" authority="Linnaeus" date="1754">mirabilis</taxon_name>
    <taxon_name rank="species" authority="S. Watson" date="1876">greenei</taxon_name>
    <place_of_publication>
      <publication_title>Proc. Amer. Acad. Arts</publication_title>
      <place_in_publication>12: 253. 1876</place_in_publication>
    </place_of_publication>
    <taxon_hierarchy>family nyctaginaceae;genus mirabilis;species greenei</taxon_hierarchy>
  </taxon_identification>
  <description type="morphology">Herbs, forming hemispheric clumps 6–8 dm diam., glabrous to sparsely puberulent. Stems 4–8 dm. Leaves spreading; petioles of proximal leaves 1–2.7 cm; blades of midstem leaves widely elliptic to ovate, 3–8-5 × 3–5.5 cm, base obtuse, often asymmetric, apex acute or acuminate. Involucres: peduncle 25–85 mm; involucres erect or ascending, 26–40 mm; bracts 5, 50% connate, apex acute to widely ovate. Flowers 6(–16) per involucre; perianth magenta, funnelform, 4–5 cm. Fruits light brown, with 5 blunt angles and 10 slender ribs visible when wet, widely obovoid to widely ellipsoid, 7–7.5 mm, tuberculate, glabrous or very sparsely puberulent, secreting mucilage most abundantly on ribs when wetted. 2n = 66.</description>
  <description type="phenology">late spring</description>
  <description type="habitat">gravelly slopes and flats</description>
  <description type="habitat">with juniper</description>
  <description type="elevation">400–1000 m;</description>
  <description type="distribution">Calif.</description>
  <number>6.</number>
  <discussion>Mirabilis greenei may have as many as sixteen flowers per involucral bract.</discussion>
</bio:treatment>
