<?xml version="1.0" encoding="UTF-8"?>
<bio:treatment xmlns:bio="http://www.github.com/biosemantics" xmlns:xsi="http://www.w3.org/2001/XMLSchema-instance" xsi:schemaLocation="http://www.github.com/biosemantics http://www.w3.org/2001/XMLSchema-instance">
  <meta>
    <source>
      <author>unknown</author>
      <date>unknown</date>
    </source>
  </meta>
  <taxon_identification status="ACCEPTED">
    <taxon_name rank="family" authority="Jussieu" date="unknown">orchidaceae</taxon_name>
    <taxon_name rank="genus" authority="Lindley" date="1833">tropidia</taxon_name>
    <taxon_name rank="species" authority="(Swartz) Ames" date="1908">polystachya</taxon_name>
    <place_of_publication>
      <publication_title>Orchidaceae</publication_title>
      <place_in_publication>2: 262. 1908</place_in_publication>
    </place_of_publication>
    <taxon_hierarchy>family orchidaceae;genus tropidia;species polystachya</taxon_hierarchy>
  </taxon_identification>
  <taxon_identification status="BASIONYM">
    <taxon_name rank="genus" authority="unknown" date="unknown">Serapias</taxon_name>
    <taxon_name rank="species" authority="Swartz" date="unknown">polystachya</taxon_name>
    <place_of_publication>
      <publication_title>Prodr.,</publication_title>
      <place_in_publication>119. 1788</place_in_publication>
    </place_of_publication>
    <taxon_hierarchy>genus Serapias;species polystachya;</taxon_hierarchy>
  </taxon_identification>
  <taxon_identification status="SYNONYM">
    <taxon_name rank="genus" authority="unknown" date="unknown">Chloidia</taxon_name>
    <taxon_name rank="species" authority="(Swartz) Reichenbach f." date="unknown">polystachya</taxon_name>
    <taxon_hierarchy>genus Chloidia;species polystachya;</taxon_hierarchy>
  </taxon_identification>
  <taxon_identification status="SYNONYM">
    <taxon_name rank="genus" authority="unknown" date="unknown">Chloidia</taxon_name>
    <taxon_name rank="species" authority="Lindley" date="unknown">vernalis</taxon_name>
    <taxon_hierarchy>genus Chloidia;species vernalis;</taxon_hierarchy>
  </taxon_identification>
  <taxon_identification status="SYNONYM">
    <taxon_name rank="genus" authority="unknown" date="unknown">Corymbis</taxon_name>
    <taxon_name rank="species" authority="(Swartz) Bentham ex Fawcett" date="unknown">polystachya</taxon_name>
    <taxon_hierarchy>genus Corymbis;species polystachya;</taxon_hierarchy>
  </taxon_identification>
  <taxon_identification status="SYNONYM">
    <taxon_name rank="genus" authority="unknown" date="unknown">Corymborchis</taxon_name>
    <taxon_name rank="species" authority="(Swartz) Kuntze" date="unknown">polystachya</taxon_name>
    <taxon_hierarchy>genus Corymborchis;species polystachya;</taxon_hierarchy>
  </taxon_identification>
  <taxon_identification status="SYNONYM">
    <taxon_name rank="genus" authority="unknown" date="unknown">Macrostylis</taxon_name>
    <taxon_name rank="species" authority="(Lindley) Reichenbach f." date="unknown">vernalis</taxon_name>
    <taxon_hierarchy>genus Macrostylis;species vernalis;</taxon_hierarchy>
  </taxon_identification>
  <taxon_identification status="SYNONYM">
    <taxon_name rank="genus" authority="unknown" date="unknown">Neottia</taxon_name>
    <taxon_name rank="species" authority="(Swartz) Swartz" date="unknown">polystachya</taxon_name>
    <taxon_hierarchy>genus Neottia;species polystachya;</taxon_hierarchy>
  </taxon_identification>
  <taxon_identification status="SYNONYM">
    <taxon_name rank="genus" authority="unknown" date="unknown">Polystachya</taxon_name>
    <taxon_name rank="species" authority="A. Richard" date="unknown">membranacea</taxon_name>
    <taxon_hierarchy>genus Polystachya;species membranacea;</taxon_hierarchy>
  </taxon_identification>
  <taxon_identification status="SYNONYM">
    <taxon_name rank="genus" authority="unknown" date="unknown">Stenorrhynchos</taxon_name>
    <taxon_name rank="species" authority="(Swartz) Sprengel" date="unknown">polystachyon</taxon_name>
    <taxon_hierarchy>genus Stenorrhynchos;species polystachyon;</taxon_hierarchy>
  </taxon_identification>
  <taxon_identification status="SYNONYM">
    <taxon_name rank="genus" authority="unknown" date="unknown">Tomotris</taxon_name>
    <taxon_name rank="species" authority="(Swartz) Rafinesque" date="unknown">polystachya</taxon_name>
    <taxon_hierarchy>genus Tomotris;species polystachya;</taxon_hierarchy>
  </taxon_identification>
  <taxon_identification status="SYNONYM">
    <taxon_name rank="genus" authority="unknown" date="unknown">Tropidia</taxon_name>
    <taxon_name rank="species" authority="Ames" date="unknown">eatonii</taxon_name>
    <taxon_hierarchy>genus Tropidia;species eatonii;</taxon_hierarchy>
  </taxon_identification>
  <description type="morphology">Plants to 70 cm. Roots several from rhizome, brown, 0.5–3 mm diam., villous. Rhizomes 2.5–4 mm diam. Stems partially concealed by bladeless tubular sheaths proximally when young, naked when older, covered by leaf sheaths distally, usually branched, terete, 31–55 cm × 2–4 mm. Leaves several; sheaths clasping stem, 4–4.5 cm; blade oblong-lanceolate, 6–27 × 2.4–6.7 cm, apex acuminate. Inflorescences: peduncles 3.5–14 cm; panicles 3–48-flowered, dense, subglobular, 2.5–9 × 3–6.5 cm; floral bracts linear to lanceolate, 4–10 mm, apex acuminate to subulate. Flowers 8–12 mm; sepals greenish white, 5-veined; dorsal sepal concave, oblong to elliptic, 6.5–7 × 2–2.5 mm, apex acute to obtuse; lateral sepals somewhat gibbous, lanceolate-oblong, slightly falcate, 5.5–6.5 × 1.7–2 mm, apex acute; petals white, 3-veined, somewhat falcate, lanceolate to elliptic-oblanceolate, 5–6 × 1.5–2 mm, apex acute; lip embracing column, white with yellow spot on disc, oblong, 4.5–6 × 2 mm, constricted at middle, apex retuse, sometimes obscurely 4-lobed; disc 2-lamellate and flabellate distally; column 4–4.5 mm. Capsules ribbed, 10–14 × 3–6 mm.</description>
  <description type="phenology">Flowering Sep--Mar.</description>
  <description type="habitat">Moist hardwood hammocks;</description>
  <description type="elevation">0--20 m;</description>
  <description type="distribution">Fla.; Mexico; West Indies; Central America; South America (Galapagos Islands).</description>
  <number>1.</number>
  <other_name type="common_name">Young palm orchid</other_name>
</bio:treatment>
