<?xml version="1.0" encoding="UTF-8"?>
<bio:treatment xmlns:bio="http://www.github.com/biosemantics" xmlns:xsi="http://www.w3.org/2001/XMLSchema-instance" xsi:schemaLocation="http://www.github.com/biosemantics http://www.w3.org/2001/XMLSchema-instance">
  <meta>
    <source>
      <author>unknown</author>
      <date>unknown</date>
    </source>
  </meta>
  <taxon_identification status="ACCEPTED">
    <taxon_name rank="family" authority="Burnett" date="unknown">Brassicaceae</taxon_name>
    <taxon_name rank="tribe" authority="de Candolle" date="unknown">Arabideae</taxon_name>
    <taxon_name rank="genus" authority="unknown" date="unknown">Draba</taxon_name>
    <taxon_name rank="species" authority="A. Heller" date="unknown">viridis</taxon_name>
    <place_of_publication>
      <publication_title>Muhlenbergia</publication_title>
      <place_in_publication>1: 27. 1901</place_in_publication>
    </place_of_publication>
    <taxon_hierarchy>family Brassicaceae;tribe Arabideae;genus Draba;species viridis;</taxon_hierarchy>
  </taxon_identification>
  <taxon_identification status="SYNONYM">
    <taxon_name rank="genus" authority="unknown" date="unknown">Draba</taxon_name>
    <taxon_name rank="species" authority="Greene" date="unknown">petrophila</taxon_name>
    <taxon_name rank="variety" authority="(A. Heller) C. L. Hitchcock" date="unknown">viridis</taxon_name>
    <taxon_hierarchy>genus Draba;species petrophila;variety viridis;</taxon_hierarchy>
  </taxon_identification>
  <number>118.</number>
  <discussion type="conservation">of conservation concern;</discussion>
  <discussion>Draba viridis has been reported from the Huachuca and Santa Catalina mountains in southern Arizona, and the adjacent San Jose Mountains in Sonora, Mexico. It was reduced to a variety of D. petrophila by Hitchcock and a form of D. helleriana by O. E. Schulz, but is easily separated from both (I. A. Al-Shehbaz and M. D. Windham 2007).</discussion>
</bio:treatment>
